CONTRIBUTING.md
LICENSE
README.md
heimdallm/__init__.py
heimdallm/bifrost.py
heimdallm/bifrosts/sql/__init__.py
heimdallm/bifrosts/sql/bifrost.py
heimdallm/bifrosts/sql/common.py
heimdallm/bifrosts/sql/envelope.py
heimdallm/bifrosts/sql/envelopes/sql/mysql/select.j2
heimdallm/bifrosts/sql/envelopes/sql/postgres/select.j2
heimdallm/bifrosts/sql/envelopes/sql/sqlite/select.j2
heimdallm/bifrosts/sql/envelopes/sql/test.j2
heimdallm/bifrosts/sql/exc.py
heimdallm/bifrosts/sql/mysql/__init__.py
heimdallm/bifrosts/sql/mysql/presets.py
heimdallm/bifrosts/sql/mysql/select/__init__.py
heimdallm/bifrosts/sql/mysql/select/bifrost.py
heimdallm/bifrosts/sql/mysql/select/envelope.py
heimdallm/bifrosts/sql/mysql/select/grammar.lark
heimdallm/bifrosts/sql/mysql/select/validator.py
heimdallm/bifrosts/sql/postgres/__init__.py
heimdallm/bifrosts/sql/postgres/presets.py
heimdallm/bifrosts/sql/postgres/select/__init__.py
heimdallm/bifrosts/sql/postgres/select/bifrost.py
heimdallm/bifrosts/sql/postgres/select/envelope.py
heimdallm/bifrosts/sql/postgres/select/grammar.lark
heimdallm/bifrosts/sql/postgres/select/validator.py
heimdallm/bifrosts/sql/reconstruct.py
heimdallm/bifrosts/sql/sqlite/__init__.py
heimdallm/bifrosts/sql/sqlite/presets.py
heimdallm/bifrosts/sql/sqlite/select/__init__.py
heimdallm/bifrosts/sql/sqlite/select/bifrost.py
heimdallm/bifrosts/sql/sqlite/select/envelope.py
heimdallm/bifrosts/sql/sqlite/select/grammar.lark
heimdallm/bifrosts/sql/sqlite/select/validator.py
heimdallm/bifrosts/sql/utils/__init__.py
heimdallm/bifrosts/sql/utils/context.py
heimdallm/bifrosts/sql/utils/identifier.py
heimdallm/bifrosts/sql/validator.py
heimdallm/bifrosts/sql/visitors/__Init__.py
heimdallm/bifrosts/sql/visitors/aliases.py
heimdallm/bifrosts/sql/visitors/ambiguity.py
heimdallm/bifrosts/sql/visitors/facets.py
heimdallm/bifrosts/sql/visitors/id_setter.py
heimdallm/bifrosts/sql/visitors/parent.py
heimdallm/constraints.py
heimdallm/context.py
heimdallm/envelope.py
heimdallm/llm.py
heimdallm-1.0.3.dist-info/LICENSE
heimdallm-1.0.3.dist-info/METADATA
heimdallm-1.0.3.dist-info/WHEEL
heimdallm-1.0.3.dist-info/RECORD
