Metadata-Version: 2.1
Name: heimdallm
Version: 1.0.3
Summary: Construct trusted SQL queries from untrusted input
Home-page: https://github.com/amoffat/HeimdaLLM
License: AGPL-3.0
Keywords: sql,llm,ai
Author: Andrew Moffat
Author-email: arwmoffat@gmail.com
Maintainer: Andrew Moffat
Maintainer-email: arwmoffat@gmail.com
Requires-Python: >=3.10,<4.0
Classifier: Development Status :: 4 - Beta
Classifier: Intended Audience :: Developers
Classifier: License :: OSI Approved :: GNU Affero General Public License v3
Classifier: License :: OSI Approved :: GNU Affero General Public License v3 or later (AGPLv3+)
Classifier: Programming Language :: Python
Classifier: Programming Language :: Python :: 3
Classifier: Programming Language :: Python :: 3.10
Classifier: Programming Language :: Python :: 3.11
Classifier: Programming Language :: Python :: 3.12
Classifier: Programming Language :: Python :: 3.8
Classifier: Programming Language :: Python :: 3.9
Classifier: Topic :: Software Development :: Libraries :: Python Modules
Requires-Dist: jinja2 (>=3.1.2,<4.0.0)
Requires-Dist: lark (>=1.1.5,<2.0.0)
Requires-Dist: openai (>=0.27.8,<0.28.0)
Requires-Dist: structlog (>=23.1.0,<24.0.0)
Project-URL: Documentation, https://heimdallm.readthedocs.io/en/latest/
Project-URL: Repository, https://github.com/amoffat/HeimdaLLM
